{
  "title": "강화군 피해지원금 2026: 대상·금액·신청 방법 총정리",
  "slug": "damage-relief-ganghwa-2026",
  "metaDescription": "강화군이 군수 공백 상황에서도 피해지원금 현장 지급을 추진 중입니다. 지원 대상, 금액, 신청 방법을 한눈에 정리했습니다. 놓치지 마세요.",
  "tldr": [
    "강화군은 군수 공백 중에도 피해지원금 현장 집행을 지속하고 있습니다.",
    "지원금은 피해를 입은 주민·소상공인을 대상으로 현장 밀착 방식으로 지급됩니다.",
    "구체적인 지원 금액과 신청 방법은 강화군청 공식 안내를 통해 확인해야 합니다.",
    "2026년 4월 29일 기준 강화군은 민생 지원을 최우선 과제로 추진 중입니다."
  ],
  "category": "자산",
  "tags": [
    "피해지원금",
    "강화군",
    "재난지원",
    "민생지원",
    "지역지원금",
    "2026지원금"
  ],
  "coreFacts": {
    "who": "강화군 내 피해를 입은 주민 및 소상공인·자영업자",
    "amount": "공식 사이트 또는 강화군청 담당 부서에서 확인 필요",
    "deadline": "강화군청 공식 공고 기준으로 확인 필요",
    "where": "강화군청 및 현장 방문 접수 (강화군청 032-930-3114)"
  },
  "freshness": {
    "trendingTerm": "피해지원금",
    "daysActive": 1,
    "totalCount": 13,
    "rankToday": 1
  },
  "sections": [
    {
      "heading": "강화군 피해지원금이란 무엇인가요?",
      "lead": "강화군은 군수 공백 상황에서도 피해 주민에 대한 지원금 집행을 멈추지 않고 현장 밀착 행보를 이어가고 있습니다.",
      "body": "2026년 4월 29일 보도에 따르면, 강화군은 군수 부재라는 행정 공백 상황에서도 피해지원금 지급 업무를 전력으로 추진하고 있습니다. 민생 안정을 최우선 과제로 삼아 담당 공무원들이 현장을 직접 방문하는 방식으로 집행하고 있습니다.\n\n이번 지원금은 재난·피해 등으로 경제적 어려움을 겪는 주민과 소상공인을 대상으로 합니다. 행정 공백에도 불구하고 주민 피해 회복을 위한 지원이 지속된다는 점에서 의미가 있습니다.\n\n강화군은 현장 중심 행정을 통해 지원이 필요한 주민에게 신속하게 자금이 전달될 수 있도록 노력하고 있습니다. 지원 규모와 구체적인 피해 유형별 기준은 강화군청 공식 발표를 통해 확인할 수 있습니다."
    },
    {
      "heading": "누가 받을 수 있나요?",
      "lead": "피해를 입은 강화군 주민 및 소상공인·자영업자가 주요 대상입니다.",
      "body": "현재 보도된 내용을 기준으로, 강화군 피해지원금의 대상은 실제 피해를 입은 지역 주민과 소상공인입니다. 재난, 경기 침체, 기타 외부 요인으로 인해 생계·영업에 타격을 받은 경우가 해당될 수 있습니다.\n\n자영업자, 소상공인, 1인 사업자 등 매출 감소나 영업 피해를 입은 분들도 지원 대상에 포함될 가능성이 높습니다. 정확한 자격 요건은 강화군청에서 공고하는 지원 기준을 직접 확인해야 합니다.\n\n주민등록상 강화군 거주자 또는 강화군 내에서 사업을 영위하는 사업자인지 여부가 핵심 요건이 될 것으로 예상됩니다. 세부 기준은 강화군청 공식 안내문 및 담당 부서에 문의해 확인하시기 바랍니다."
    },
    {
      "heading": "얼마를 받을 수 있나요?",
      "lead": "구체적인 지원 금액은 강화군청 공식 발표를 통해 확인해야 하며, 현재 보도에서는 금액이 명시되지 않았습니다.",
      "body": "2026년 4월 29일 기준 보도에서는 피해지원금의 정확한 금액이 공개되지 않았습니다. 피해지원금 규모는 피해 유형, 피해 규모, 가구 구성 등에 따라 달라질 수 있습니다.\n\n유사한 지자체 피해지원금 사례를 보면 가구당 수십만 원에서 수백만 원까지 다양하게 책정됩니다. 강화군의 정확한 지원 금액은 강화군청 공식 공고 또는 담당 부서에 직접 문의하여 확인하는 것이 가장 정확합니다.\n\n지원 금액이 공식 발표되면 이 페이지를 즉시 업데이트할 예정입니다."
    },
    {
      "heading": "어떻게 신청하나요?",
      "lead": "강화군청 현장 방문 또는 담당 부서 문의를 통해 신청할 수 있습니다.",
      "body": "현재 강화군은 현장 밀착 방식으로 피해지원금을 집행하고 있습니다. 이는 담당 공무원이 직접 피해 현장을 방문하거나, 주민이 강화군청을 방문하여 접수하는 방식을 의미합니다.\n\n신청 시에는 피해 사실을 증빙하는 서류(피해 사진, 영업 손실 증빙, 주민등록등본 등)를 준비하는 것이 일반적입니다. 정확한 구비 서류 목록은 강화군청 담당 부서에 사전 문의하는 것을 권장합니다.\n\n강화군청 대표 전화(032-930-3114)로 연락하거나 강화군청 홈페이지 공지사항을 확인하면 신청 절차 및 접수 기간 등 상세 안내를 받을 수 있습니다."
    },
    {
      "heading": "주의할 점·놓치기 쉬운 항목",
      "lead": "신청 기간과 구비 서류를 미리 확인하지 않으면 지원금을 놓칠 수 있습니다.",
      "body": "피해지원금은 대부분 신청 기간이 정해져 있습니다. 기간이 지나면 소급 신청이 불가능한 경우가 많으므로, 공고가 나오는 즉시 신청 일정을 확인하는 것이 중요합니다.\n\n군수 공백 상황으로 인해 행정 처리 속도가 다소 지연될 수 있습니다. 강화군청 담당 부서에 미리 연락해 진행 상황을 확인하는 것이 좋습니다.\n\n지원금과 별개로, 피해 규모 입증을 위한 서류(영수증, 피해 사진, 매출 감소 증빙 등)는 가능한 한 빠르게 확보해 두어야 합니다. 사후에 증빙 자료를 수집하기 어려운 경우가 많습니다."
    }
  ],
  "table": {
    "title": "강화군 피해지원금 핵심 정보 한눈에",
    "headers": [
      "항목",
      "내용"
    ],
    "rows": [
      [
        "대상",
        "강화군 내 피해 주민 및 소상공인·자영업자"
      ],
      [
        "금액",
        "강화군청 공식 공고 확인 필요"
      ],
      [
        "기간",
        "강화군청 공식 공고 확인 필요"
      ],
      [
        "신청처",
        "강화군청 방문 또는 현장 접수 (032-930-3114)"
      ],
      [
        "담당기관",
        "강화군청 (인천광역시 강화군)"
      ]
    ]
  },
  "faq": [
    {
      "q": "강화군에 주민등록이 되어 있지 않아도 신청할 수 있나요?",
      "a": "일반적으로 피해지원금은 주민등록 또는 사업장 소재지 기준으로 지급됩니다. 정확한 요건은 강화군청 담당 부서(032-930-3114)에 직접 문의해 확인하시기 바랍니다."
    },
    {
      "q": "군수가 없는 상황에서도 지원금이 정상 지급되나요?",
      "a": "네. 2026년 4월 29일 보도에 따르면, 강화군은 군수 공백 중에도 피해지원금 현장 집행을 지속하고 있습니다. 담당 공무원들이 정상적으로 업무를 수행 중입니다."
    },
    {
      "q": "온라인으로도 신청할 수 있나요?",
      "a": "현재 보도에서는 현장 중심 집행 방식이 강조되었습니다. 온라인 신청 가능 여부는 강화군청 홈페이지 공지사항 또는 담당 부서에 직접 문의해 확인하시기 바랍니다."
    },
    {
      "q": "피해지원금을 받으면 다른 지원금 신청에 영향이 있나요?",
      "a": "일부 지원금은 중복 수혜 제한이 있을 수 있습니다. 강화군 피해지원금과 다른 정부 지원금을 함께 신청할 경우, 각 지원 기관에 중복 수령 가능 여부를 반드시 확인하세요."
    },
    {
      "q": "지원 금액과 신청 기간은 언제 공개되나요?",
      "a": "강화군청 공식 공고를 통해 발표될 예정입니다. 강화군청 홈페이지(강화군청 공지사항) 또는 대표 전화(032-930-3114)를 통해 최신 정보를 확인하시기 바랍니다."
    }
  ],
  "relatedSubsidies": [
    "savings-account"
  ],
  "relatedPersonas": [
    "office-rookie",
    "self-employed"
  ],
  "sources": [
    {
      "title": "군수 공백에도 '민생'은 전력질주… 강화군, 피해지원금 현장 밀착 행보",
      "url": "http://www.paxetv.com/news/articleView.html?idxno=270937",
      "publisher": "팍스경제TV",
      "pubDate": "2026-04-29"
    }
  ],
  "publishedAt": "2026-04-29T07:52:48.564Z",
  "date": "2026-04-29"
}
