{
  "id": "reduction-000012",
  "applyUrl": "https://www.gov.kr/portal/rcvfvrSvc/dtlEx/172100000012",
  "title": "취약계층 통신요금감면",
  "agency": "과학기술정보통신부",
  "category": "복지",
  "icon": "cat-welfare",
  "bg": "bg-5",
  "amount": 33500,
  "amountLabel": "월 지원",
  "period": "",
  "deadline": "상시신청",
  "summary": "취약계층 요금감면 신청자에 한해 통신요금감면 지원",
  "eligibility": [
    "ㅇ 기초생활수급자(생계) : 국민기초생활보장법에 따른 소득인정액이 기준 중위소득의 30% 이하인 사람",
    "ㅇ 기초생활수급자(의료) : 국민기초생활보장법에 따른 소득인정액이 기준 중위소득의 40% 이하인 사람",
    "ㅇ 기초생활수급자(주거) : 국민기초생활보장법에 따른 소득인정액이 기준 중위소득의 43% 이하인 사람",
    "ㅇ 기초생활수급자(교육) : 국민기초생활보장법에 따른 소득인정액이 기준 중위소득의 50% 이하인 사람",
    "ㅇ 차상위 계층 : 국민기초생활보장에 따라 소득인정액이 기준 중위소득의 50% 이하이며, 아래 법률에 따라 지원을 받는 사람 및 그 가구원",
    "국민기초생활보장법에 따른 자활에 필요한 사업에 참가하는 사람"
  ],
  "benefits": [
    "ㅇ 장애인, 국가유공자 : 시내전화(월 통화료 50% 감면), 시외전화(월 통화료 3만원 한도 50% 감면), 인터넷전화(월 통화료 50% 감면), 이동전화(기본료 및 통화료 35% 감면), 초고속인터넷(월 이용료 30% 감면)",
    "ㅇ 기초생활수급자(생계, 의료) : 시내전화(가입비 및 기본료 면제, 시내통화 75도수(225분) 무료), 시외전화(시외통화 75도수(225분) 무료), 인터넷전화(가입비 및 기본료 면제, 시내외통화 150도수(450분) 무료), 이동전화(기본감면(26,000원) 및 통화료 50% 감면, 월 최대 33,500원 한도),  초고속인터넷(월 이용료 30% 감면)",
    "ㅇ 기초생활수급자(주거, 교육) 및 차상위계층 : 이동전화(기본감면(11,000원) 및 통화료 35% 감면, 월 최대 21,500원 한도)",
    "ㅇ 기초연금수급자 : 이동전화(기본료 및 통화료 50% 감면, 월 최대 11,000원 한도)"
  ],
  "documents": [],
  "status": "신청 가능",
  "tags": [
    "복지",
    "개인",
    "현금지원",
    "감면"
  ],
  "targetPersonas": []
}
