{
  "id": "vocational-allowance-005001",
  "applyUrl": "https://www.gov.kr/portal/rcvfvrSvc/dtlEx/149200005001",
  "title": "직업능력개발수당",
  "agency": "고용노동부",
  "category": "창업",
  "icon": "cat-startup",
  "bg": "bg-3",
  "amount": 0,
  "amountLabel": "지원금",
  "period": "",
  "deadline": "정확한 날짜는 개인별 수급기간 등에 따라 달라짐",
  "summary": "구직급여 수급자 중 직업능력개발훈련을 받는 수급자에게 수당 지원(1일 7,530원)지급",
  "eligibility": ["수급자격자가 직업안정기관장이 지시한 훈련을 받는 경우 교통비와 식대 지원"],
  "benefits": ["훈련을 받은 날 1일 7,530원 지급"],
  "documents": [],
  "status": "신청 가능",
  "tags": ["창업", "개인", "현금지원"],
  "targetPersonas": ["office-rookie", "low-income"]
}
